operacionesmarlon/__init__.py
operacionesmarlon/modulo.py
operacionesmarlon-0.1.0.dist-info/METADATA
operacionesmarlon-0.1.0.dist-info/WHEEL
operacionesmarlon-0.1.0.dist-info/top_level.txt
operacionesmarlon-0.1.0.dist-info/RECORD
