Metadata-Version: 2.4
Name: operacionesmarlon
Version: 0.1.0
Summary: libreria de operaciones básicas
Author: Marlon García
License: UdeA
Requires-Python: >=3.11.13
Dynamic: author
Dynamic: description
Dynamic: description-content-type
Dynamic: license
Dynamic: requires-python
Dynamic: summary
